DipoleAmplitudePredictor/__init__.py
DipoleAmplitudePredictor/model.py
DipoleAmplitudePredictor-0.2.1.dist-info/METADATA
DipoleAmplitudePredictor-0.2.1.dist-info/WHEEL
DipoleAmplitudePredictor-0.2.1.dist-info/top_level.txt
DipoleAmplitudePredictor-0.2.1.dist-info/RECORD
